nslr
