Metadata-Version: 1.0
Name: nslr
Version: 0.0.3
Summary: Naive Segmented Linear Regression
Home-page: https://gitlab.com/nslr/nslr
Author: Jami Pekkanen
Author-email: jami.pekkanen@gmail.com
License: UNKNOWN
Platform: any
